{
  "circle": 3,
  "school": "Воплощение",
  "castingTime": "1 действие",
  "range": "150 футов",
  "components": "В, С, М (крошечный шарик из гуано летучей мыши и серы)",
  "duration": "Мгновенная",
  "circles": [
    "Тайное"
  ],
  "effect": [
    "Яркая полоса вспыхивает из вашего указывающего пальца в точку, выбранную вами в пределах дистанции, а затем расцветает с низким ревом во взрыв пламени. Каждое существо в 20-футовой сфере с центром в этой точке должно совершить спасбросок Ловкости. Цель получает 8к6 урона огнем при проваленном спасброске, или половину этого урона при успешном.Огонь распространяется за углы. Он поджигает легковоспламеняющиеся объекты в области, которые никто не носит и не несет.",
    "На более высоких кругах.",
    "Когда вы накладываете это заклинание, используя ячейку заклинания 4-го круга или выше, урон увеличивается на 1к6 за каждый круг ячейки выше 3-го."
  ],
  "type": "spell",
  "id": "BFRD:spell/ognennyy-shar",
  "slug": "ognennyy-shar",
  "name": "Огненный шар",
  "schemaVersion": "1.0.0",
  "src": {
    "abbr": "BFRD",
    "name": "Black Flag Reference Document",
    "version": "1.0",
    "url": "https://bfrd.net/",
    "license": "Open RPG Creative License (ORC)",
    "hash": "f14417d92b42d63d38b9e91b15bbf4ad49cec69d9f7d1d7486a81784017cfc27"
  },
  "sourceFile": "input/spells/spells_F.md"
}