{
  "circle": 2,
  "school": "Вызов",
  "castingTime": "1 действие",
  "range": "60 футов",
  "components": "В, С, М (кусочек паутины)",
  "duration": "Концентрация, до 1 часа",
  "circles": [
    "Тайное"
  ],
  "effect": [
    "Вы вызываете массу густой, липкой паутины в точке по вашему выбору в пределах дистанции. Паутина заполняет 20-футовый куб от этой точки на время действия заклинания. Паутина является труднопроходимой местностью и слегка заслоняет свою область. Если паутина не закреплена между двумя твердыми массами (такими как стены или деревья) или не наслоена на пол, стену или потолок, вызванная паутина рушится сама на себя, и заклинание заканчивается в начале вашего следующего хода. Паутина, наслоенная на плоскую поверхность, имеет глубину 3 фута.Каждое существо, которое начинает свой ход в паутине или входит в нее во время своего хода, должно совершить спасбросок Ловкости. При проваленном спасброске существо опутано, пока остается в паутине или пока не освободится. Существо, опутанное паутиной, может использовать свое действие, чтобы совершить проверку Силы против Сл спасброска от вашего заклинания. Если оно преуспевает, оно больше не опутано.Паутина легковоспламеняема. Любой 5-футовый куб паутины, подвергшийся воздействию огня, сгорает за 1 раунд, нанося 2к4 урона огнем любому существу, которое начинает свой ход в огне."
  ],
  "type": "spell",
  "id": "BFRD:spell/pautina",
  "slug": "pautina",
  "name": "Паутина",
  "schemaVersion": "1.0.0",
  "src": {
    "abbr": "BFRD",
    "name": "Black Flag Reference Document",
    "version": "1.0",
    "url": "https://bfrd.net/",
    "license": "Open RPG Creative License (ORC)",
    "hash": "65e24979b5d5e825b6ba707999d9446416378aa470284b4196bd58407cfdcb81"
  },
  "sourceFile": "input/spells/spells_T-Z.md"
}