{
  "circle": 9,
  "school": "Вызов",
  "castingTime": "1 действие",
  "range": "60 футов",
  "components": "В, С, М (алмаз стоимостью не менее 5000 зм)",
  "duration": "Концентрация, до 1 часа",
  "circles": [
    "Тайное",
    "Потустороннее"
  ],
  "effect": [
    "Вы вызываете портал, связывающий незанятое пространство, которое вы можете видеть в пределах дистанции, с точным местоположением на другом плане существования. Портал представляет собой круглое отверстие, которое вы можете сделать диаметром от 5 до 20 футов. Вы можете ориентировать портал в любом выбранном вами направлении. Портал существует на время действия заклинания.Портал имеет переднюю и заднюю стороны на каждом плане, где он появляется. Путешествие через портал возможно только путем прохождения через его переднюю сторону. Все, что делает это, мгновенно переносится на другой план, появляясь в ближайшем к порталу незанятом пространстве.Божества и другие правители планов могут предотвратить открытие порталов, созданных этим заклинанием, в их присутствии или где-либо в их владениях.Когда вы накладываете это заклинание, вы можете произнести имя конкретного существа (псевдоним, титул или прозвище не работают). Если это существо находится на плане, отличном от того, на котором находитесь вы, портал открывается в непосредственной близости от названного существа и притягивает существо сквозь него в ближайшее незанятое пространство на вашей стороне портала. Вы не получаете особой власти над существом, и оно свободно действовать так, как сочтет нужным Мастер. Оно может уйти, атаковать вас или помочь вам."
  ],
  "type": "spell",
  "id": "BFRD:spell/vrata",
  "slug": "vrata",
  "name": "Врата",
  "schemaVersion": "1.0.0",
  "src": {
    "abbr": "BFRD",
    "name": "Black Flag Reference Document",
    "version": "1.0",
    "url": "https://bfrd.net/",
    "license": "Open RPG Creative License (ORC)",
    "hash": "28b227e68e41a7f69c294b4f37dab627fc7e1af4db1ca8f6fd7cfc84970aa135"
  },
  "sourceFile": "input/spells/spells_G.md"
}